{
  "$schema": "../registry-item.schema.json",
  "name": "drivo/icon",
  "type": "registry:ui",
  "template": "drivo",
  "files": [
    {
      "path": "components/Icon.tsx",
      "type": "registry:ui",
      "target": "components/Icon.tsx"
    }
  ],
  "dependencies": [
    "expo-router",
    "lucide-react-native"
  ],
  "registryDependencies": [
    "drivo/lib-contexts-theme-colors"
  ],
  "props": {
    "variants": [],
    "sizes": [],
    "rounded": [],
    "states": [
      "disabled"
    ]
  },
  "traits": [
    "pill",
    "outlined",
    "flat"
  ],
  "group": "elements"
}
