{
  "$schema": "../registry-item.schema.json",
  "name": "voyage/bundle-picker-sheet",
  "type": "registry:ui",
  "template": "voyage",
  "files": [
    {
      "path": "components/BundlePickerSheet.tsx",
      "type": "registry:ui",
      "target": "components/BundlePickerSheet.tsx"
    }
  ],
  "dependencies": [
    "expo-image",
    "react-native-safe-area-context"
  ],
  "registryDependencies": [
    "voyage/geo-glyph",
    "voyage/icon",
    "voyage/lib-utils-bundle-storage"
  ],
  "props": {
    "variants": [],
    "sizes": [],
    "rounded": [],
    "states": []
  },
  "traits": [],
  "group": "elements"
}
