{
  "$schema": "../registry-item.schema.json",
  "name": "expo-convex-template/floating-button",
  "type": "registry:ui",
  "template": "expo-convex-template",
  "files": [
    {
      "path": "components/FloatingButton.tsx",
      "type": "registry:ui",
      "target": "components/FloatingButton.tsx"
    }
  ],
  "dependencies": [
    "@jv/ui",
    "expo-router"
  ],
  "registryDependencies": [
    "expo-convex-template/icon",
    "expo-convex-template/themed-text"
  ],
  "props": {
    "variants": [],
    "sizes": [],
    "rounded": [],
    "states": [
      "visible",
      "isAnimated"
    ]
  },
  "traits": [
    "pill",
    "elevated",
    "animated"
  ],
  "group": "elements"
}
