{
  "$schema": "../registry-item.schema.json",
  "name": "feedy/placeholder",
  "type": "registry:ui",
  "template": "feedy",
  "files": [
    {
      "path": "components/Placeholder.tsx",
      "type": "registry:ui",
      "target": "components/Placeholder.tsx"
    }
  ],
  "dependencies": [
    "expo-router"
  ],
  "registryDependencies": [
    "feedy/button",
    "feedy/icon",
    "feedy/themed-text"
  ],
  "props": {
    "variants": [],
    "sizes": [],
    "rounded": [],
    "states": []
  },
  "traits": [
    "pill",
    "outlined",
    "flat"
  ],
  "group": "elements"
}
