{
  "$schema": "../registry-item.schema.json",
  "name": "feedy/screen-drawer-tabs-notifications",
  "type": "registry:screen",
  "template": "feedy",
  "files": [
    {
      "path": "app/(drawer)/(tabs)/notifications.tsx",
      "type": "registry:screen",
      "target": "app/(drawer)/(tabs)/notifications.tsx"
    },
    {
      "path": "assets/img/user-1.jpg",
      "type": "registry:asset",
      "target": "assets/img/user-1.jpg"
    },
    {
      "path": "assets/img/user-2.jpg",
      "type": "registry:asset",
      "target": "assets/img/user-2.jpg"
    },
    {
      "path": "assets/img/user-3.jpg",
      "type": "registry:asset",
      "target": "assets/img/user-3.jpg"
    }
  ],
  "dependencies": [],
  "registryDependencies": [
    "feedy/animated-view",
    "feedy/avatar",
    "feedy/header",
    "feedy/icon",
    "feedy/section",
    "feedy/theme-scroller",
    "feedy/themed-text"
  ],
  "category": "notifications",
  "route": "/notifications",
  "kind": "tab",
  "traits": [
    "soft-rounded",
    "outlined",
    "flat"
  ]
}
